osn_requests/__init__.py
osn_requests/functions.py
osn_requests/proxies.py
osn_requests/types.py
osn_requests/headers/__init__.py
osn_requests/headers/functions.py
osn_requests/headers/types.py
osn_requests/headers/accept/__init__.py
osn_requests/headers/accept/data.py
osn_requests/headers/accept_charset/__init__.py
osn_requests/headers/accept_charset/data.py
osn_requests/headers/accept_encoding/__init__.py
osn_requests/headers/accept_encoding/data.py
osn_requests/headers/accept_language/__init__.py
osn_requests/headers/accept_language/data.py
osn_requests/headers/user_agent/__init__.py
osn_requests/headers/user_agent/browser_ua_generation.py
osn_requests/headers/user_agent/data.py
osn_requests/headers/user_agent/data_types.py
osn_requests/headers/user_agent/engine_ua_generation.py
osn_requests/headers/user_agent/errors.py
osn_requests/headers/user_agent/mozilla_ua_generation.py
osn_requests/headers/user_agent/os_ua_generation.py
osn_requests-1.1.0.dist-info/METADATA
osn_requests-1.1.0.dist-info/WHEEL
osn_requests-1.1.0.dist-info/top_level.txt
osn_requests-1.1.0.dist-info/RECORD
